{
    "repo": "kaizencycle/mobius-civic-ai-terminal",
    "generated_at": "2026-04-19T20:44:54Z",
    "cycle": "C-286",
    "stats": {
        "total_commits": 1452,
        "total_files": 1100,
        "lines_of_code": 52754,
        "api_routes": 97
    },
    "integrity": {
        "gi": 0.78,
        "mode": "yellow",
        "terminal_status": "stressed"
    },
    "agents": {
        "canonical_count": 8,
        "micro_count": 4,
        "micro_sources_total": 9
    },
    "recent_prs_merged": 85,
    "deployment_state": "unknown"
}
