{
    "repo": "kaizencycle/mobius-civic-ai-terminal",
    "generated_at": "2026-04-17T19:09:02Z",
    "cycle": "C-284",
    "stats": {
        "total_commits": 1335,
        "total_files": 954,
        "lines_of_code": 48596,
        "api_routes": 90
    },
    "integrity": {
        "gi": 0.78,
        "mode": "yellow",
        "terminal_status": "stressed"
    },
    "agents": {
        "canonical_count": 8,
        "micro_count": 4,
        "micro_sources_total": 9
    },
    "recent_prs_merged": 78,
    "deployment_state": "unknown"
}
