{
  "timestamp": "2026-07-18T14:01:03.764Z",
  "agent": "ATLAS",
  "cycle": "C-376",
  "gi": 0.91,
  "gi_pre_seed": 0.91,
  "gi_post_seed": 0.91,
  "mode": "green",
  "source": "kv",
  "anomalies": [],
  "kv_keys": {
    "ok": true,
    "available": true,
    "configured": true,
    "latencyMs": 9,
    "error": null,
    "backup_redis": {
      "configured": true,
      "mirror_enabled": true,
      "read_fallback_enabled": true,
      "available": true,
      "latency_ms": 1,
      "error": null
    },
    "kv_keys_ok": false,
    "timestamp": "2026-07-18T14:03:18.386Z"
  },
  "seed_attempted": true,
  "seed_result": "200 OK (60s timeout, 30s retry)",
  "seed_seeded_keys": [
    "GI_STATE",
    "HEARTBEAT",
    "LAST_INGEST",
    "SIGNAL_SNAPSHOT"
  ],
  "sustain_eligible": true,
  "classification": "NOMINAL",
  "micro_composite": 0.846,
  "micro_cycle": "C-306",
  "degraded_agents": 0,
  "degraded_agent_names": [],
  "terminal_status": "nominal",
  "flags": {
    "integrity_source_mock": false,
    "integrity_source_kv": true,
    "integrity_source_live": false,
    "integrity_source_cached": false,
    "micro_anomaly_severity_flag": false,
    "kv_keys_ok": false,
    "kv_keys_all_ok": false,
    "tripwire_active": false,
    "gi_below_floor": false,
    "micro_operator_cycle_divergence": true
  },
  "last_journal_cycle": "C-376",
  "force_journal": false,
  "tripwire": {
    "active": false,
    "level": "none",
    "reason": "No active tripwires - baseline state",
    "last_updated": "2026-07-18T13:22:22.478Z"
  },
  "journal_status": 200,
  "journal_route": "agents/journal",
  "journal_id": "journal-ATLAS-C-376-3a283k",
  "journal_ok": true
}
