{
  "timestamp": "2026-07-09T19:05:37.000Z",
  "agent": "ATLAS",
  "cycle": "C-367",
  "gi": 0.9,
  "gi_pre_seed": 0.9,
  "gi_post_seed": 0.9,
  "mode": "green",
  "source": "kv",
  "anomalies": [],
  "kv_keys": {
    "ok": true,
    "available": true,
    "configured": true,
    "latencyMs": 3,
    "error": null,
    "backup_redis": {
      "configured": true,
      "mirror_enabled": true,
      "read_fallback_enabled": true,
      "available": true,
      "latency_ms": 3,
      "error": null
    },
    "kv_keys_ok": false,
    "timestamp": "2026-07-09T19:04:57.613Z"
  },
  "seed_attempted": true,
  "seed_result": "200 {\"ok\":true,\"seeded\":[\"GI_STATE\",\"HEARTBEAT\",\"LAST_INGEST\",\"SIGNAL_SNAPSHOT\"],\"timestamp\":\"2026-07-09T19:04:21.111Z\"} (30s timeout, 60s retry)",
  "sustain_eligible": true,
  "classification": "STRESSED",
  "micro_composite": 0.903,
  "micro_cycle": "C-306",
  "degraded_agents": 0,
  "degraded_agent_names": [],
  "terminal_status": "nominal",
  "flags": {
    "integrity_source_mock": false,
    "integrity_source_kv": true,
    "integrity_source_live": false,
    "integrity_source_cached": false,
    "micro_anomaly_severity_flag": false,
    "kv_keys_ok": false,
    "kv_keys_all_ok": false,
    "tripwire_active": false,
    "gi_below_floor": false,
    "micro_operator_cycle_divergence": true
  },
  "last_journal_cycle": "C-367",
  "force_journal": false,
  "tripwire": {
    "active": false,
    "level": "none",
    "reason": "No active tripwires - baseline state",
    "last_updated": "2026-07-09T18:12:49.149Z"
  },
  "journal_status": 200,
  "journal_route": "agents/journal",
  "journal_id": "journal-ATLAS-C-367-mjrxkk",
  "journal_ok": true,
  "journal_observe_status": 200,
  "journal_observe_id": "journal-ATLAS-C-367-mrdvn1vp1sfw",
  "journal_direct_status": 200,
  "journal_direct_id": "journal-ATLAS-C-367-mjrxkk"
}
