{
  "gi": 0.83,
  "mode": "green",
  "cycle": "C-274",
  "anomalies": [
    {
      "label": "Seismic: 38 quakes M2.5+ today, max M5.9 near 19 km WNW of Pawnee, Texas",
      "severity": "elevated"
    },
    {
      "label": "Self-ping: HTTP 401 in 63ms",
      "severity": "elevated"
    }
  ],
  "kv_keys": {
    "SIGNAL_SNAPSHOT": true,
    "GI_STATE": true,
    "ECHO_STATE": false,
    "TRIPWIRE_STATE": false,
    "HEARTBEAT": true,
    "LAST_INGEST": true
  },
  "timestamp": "2026-04-07T07:03:56.000Z"
}
